<FIR>
  <Name>Иркутск</Name>
  <ListOfAOI>
    <AOI>
      <Name>Иркутск</Name>
			<Points>
				<Point>N62000000 E145000000 0.000000</Point>
				<Point>N61000000 E146000000 0.000000</Point>
				<Point>N59173200 E145510800 0.000000</Point>
				<Point>N59220200 E144061900 0.000000</Point>
				<Point>N58564700 E142293000 0.000000</Point>
				<Point>N55450000 E138595900 0.000000</Point>
				<Point>N53180600 E136415100 0.000000</Point>
				<Point>N53052300 E137050400 0.000000</Point>
				<Point>N52381300 E140020500 0.000000</Point>
				<Point>N52245200 E140225400 0.000000</Point>
				<Point>N52095300 E140503000 0.000000</Point>
				<Point>N51475200 E141300500 0.000000</Point>
				<Point>N51080100 E141300500 0.000000</Point>
				<Point>N50535400 E139434400 0.000000</Point>
				<Point>N50183100 E139024600 0.000000</Point>
				<Point>N50243100 E136560400 0.000000</Point>
				<Point>N50530100 E135100400 0.000000</Point>
				<Point>N50420200 E134502400 0.000000</Point>
				<Point>N51162600 E134013700 0.000000</Point>
				<Point>N51320600 E132322100 0.000000</Point>
				<Point>N51544500 E131442400 0.000000</Point>
				<Point>N54400000 E128100000 0.000000</Point>
				<Point>N54510000 E129230000 0.000000</Point>
				<Point>N56100000 E131000000 0.000000</Point>
				<Point>N56550000 E131240000 0.000000</Point>
				<Point>N57160000 E131400000 0.000000</Point>
				<Point>N58000000 E132000000 0.000000</Point>
				<Point>N59100000 E135200000 0.000000</Point>
				<Point>N59450000 E138100000 0.000000</Point>
				<Point>N60510000 E139570000 0.000000</Point>
				<Point>N62000000 E142000000 0.000000</Point>
				<Point>N62000000 E145000000 0.000000</Point>
			</Points>
    </AOI>
  </ListOfAOI>
</FIR>